medoed/__init__.py
medoed/medoed.py
medoed-0.1.6.dist-info/METADATA
medoed-0.1.6.dist-info/WHEEL
medoed-0.1.6.dist-info/licenses/LICENSE
medoed-0.1.6.dist-info/RECORD
